{"openapi":"3.0.1","info":{"title":"OpenAPI definition","version":"v0"},"servers":[{"url":"http://localhost:8080","description":"Generated server url"}],"paths":{"/count-symbols":{"post":{"tags":["symbol-counter-controller"],"operationId":"countSymbols","requestBody":{"content":{"application/json":{"schema":{"$ref":"#/components/schemas/TextToDecodeDto"}}},"required":true},"responses":{"400":{"description":"Bad Request","content":{"*/*":{"schema":{"$ref":"#/components/schemas/ErrorResponse"}}}},"200":{"description":"OK","content":{"*/*":{"schema":{"$ref":"#/components/schemas/CountedSymbolsDto"}}}}}}}},"components":{"schemas":{"ErrorResponse":{"type":"object","properties":{"error":{"type":"string"}}},"TextToDecodeDto":{"required":["text"],"type":"object","properties":{"text":{"type":"string"}}},"CountedSymbolsDto":{"type":"object","properties":{"countedSymbols":{"type":"string"}}}}}}